ays_pkg/__init__.py
ays_pkg/code.py
ays_pkg/code2.py
pkg_ays/__init__.py
pkg_ays/code.py
pkg_ays/code2.py
ays_pkg-0.0.1.dist-info/METADATA
ays_pkg-0.0.1.dist-info/WHEEL
ays_pkg-0.0.1.dist-info/top_level.txt
ays_pkg-0.0.1.dist-info/RECORD
